hangul/__init__.py
hangul/test.py
hangul/tokenizer.py
hangul/data/word2idx0.json
hangul/models/model_th7.hdf5
hangul_korean-1.0rc2.dist-info/LICENSE
hangul_korean-1.0rc2.dist-info/METADATA
hangul_korean-1.0rc2.dist-info/WHEEL
hangul_korean-1.0rc2.dist-info/top_level.txt
hangul_korean-1.0rc2.dist-info/RECORD
