Metadata-Version: 2.1
Name: hangul-korean
Version: 1.0rc2
Summary: Word segmentation for the Korean Language
Home-page: https://github.com/noyongkyoon/hangul
Author: Yongkyoon No 노용균
Author-email: yno@linguist.cnu.ac.kr
License: UNKNOWN
Keywords: Korean tokenization word_segmentation
Platform: UNKNOWN
Classifier: Development Status :: 5 - Production/Stable
Classifier: Intended Audience :: Developers
Classifier: Natural Language :: Korean
Classifier: Topic :: Scientific/Engineering :: Information Analysis
Classifier: Topic :: Text Processing :: Linguistic
Classifier: Programming Language :: Python :: 3
Classifier: License :: OSI Approved :: GNU General Public License v3 or later (GPLv3+)
Classifier: Operating System :: OS Independent
Requires-Python: >=3.8
Requires-Dist: pandas
Requires-Dist: tensorflow
